pv_self_consumption_api/__init__.py
pv_self_consumption_api/client_api.py
pv_self_consumption_api/models.py
pv_self_consumption_api/pvsc.py
pv_self_consumption_api/utils.py
pv_self_consumption_api_client-0.1.5.dist-info/METADATA
pv_self_consumption_api_client-0.1.5.dist-info/WHEEL
pv_self_consumption_api_client-0.1.5.dist-info/entry_points.txt
pv_self_consumption_api_client-0.1.5.dist-info/licenses/LICENSE.txt
pv_self_consumption_api_client-0.1.5.dist-info/RECORD
