Metadata-Version: 2.1
Name: PV_self-consumption_api_client
Version: 0.1.5
Summary: PV_self-consumption API client
Author-Email: Sebastien Gardoll <sebastien@gardoll.fr>, Olivier Boucher <olivier.boucher@ipsl.fr>
License: CeCILL v2.1
Project-URL: Repository, https://github.com/OB-IPSL/PV_self_consumption_client
Project-URL: Documentation, https://github.com/OB-IPSL/PV_self_consumption_client
Requires-Python: >=3.12
Requires-Dist: pydantic>=2.9.2
Requires-Dist: pandas>=2.2.3
Requires-Dist: numpy>=2.1.1
Requires-Dist: requests>=2.32.3
Requires-Dist: matplotlib>=3.9.2
Requires-Dist: pyyaml>=6.0.2
